flock/tools/__init__.py
flock/tools/azure_tools.py
flock/tools/code_tools.py
flock/tools/file_tools.py
flock/tools/markdown_tools.py
flock/tools/system_tools.py
flock/tools/text_tools.py
flock/tools/web_tools.py
flock/tools/zendesk_tools.py
flock_mcp-0.1.7.dist-info/METADATA
flock_mcp-0.1.7.dist-info/WHEEL
flock_mcp-0.1.7.dist-info/licenses/LICENSE
flock_mcp-0.1.7.dist-info/RECORD
